COPYING
COPYING.SKK-JISYO.JIS2
COPYING.SKK-JISYO.L
COPYING.SKK-JISYO.assoc
COPYING.SKK-JISYO.geo
COPYING.SKK-JISYO.jinmei
COPYING.canossa
COPYING.termprop
COPYING.tff
MANIFEST.in
README.rst
setup.py
sentimental_skk.egg-info/PKG-INFO
sentimental_skk.egg-info/SOURCES.txt
sentimental_skk.egg-info/dependency_links.txt
sentimental_skk.egg-info/eager_resources.txt
sentimental_skk.egg-info/entry_points.txt
sentimental_skk.egg-info/not-zip-safe
sentimental_skk.egg-info/requires.txt
sentimental_skk.egg-info/top_level.txt
sskk/SKK-JISYO.JIS2
sskk/SKK-JISYO.L
sskk/SKK-JISYO.assoc
sskk/SKK-JISYO.builtin
sskk/SKK-JISYO.geo
sskk/SKK-JISYO.jinmei
sskk/__init__.py
sskk/charbuf.py
sskk/dictionary.py
sskk/eisuudb.py
sskk/input.py
sskk/kanadb.py
sskk/mode.py
sskk/output.py
sskk/romanrule.py
sskk/settings.py
sskk/sskk.py
sskk/title.py
sskk/word.py
sskk/canossa/__init__.py
sskk/canossa/setup.py
sskk/canossa/canossa/__init__.py
sskk/canossa/canossa/attribute.py
sskk/canossa/canossa/canossa.py
sskk/canossa/canossa/cell.py
sskk/canossa/canossa/constant.py
sskk/canossa/canossa/cursor.py
sskk/canossa/canossa/exception.py
sskk/canossa/canossa/iframe.py
sskk/canossa/canossa/interface.py
sskk/canossa/canossa/line.py
sskk/canossa/canossa/mouse.py
sskk/canossa/canossa/output.py
sskk/canossa/canossa/popup.py
sskk/canossa/canossa/screen.py
sskk/canossa/canossa/stub.py
sskk/canossa/canossa/termprop/__init__.py
sskk/canossa/canossa/termprop/setup.py
sskk/canossa/canossa/termprop/termprop/__init__.py
sskk/canossa/canossa/termprop/termprop/termprop.py
sskk/canossa/canossa/termprop/termprop/wcwidth.py
sskk/canossa/canossa/termprop/termprop/db/__init__.py
sskk/canossa/canossa/termprop/termprop/db/iterm2/__init__.py
sskk/canossa/canossa/termprop/termprop/db/unicode6_2/__init__.py
sskk/canossa/canossa/termprop/termprop/db/unicode6_2/cjk.py
sskk/canossa/canossa/termprop/termprop/db/unicode6_2/normal.py
sskk/canossa/canossa/tff/__init__.py
sskk/canossa/canossa/tff/setup.py
sskk/canossa/canossa/tff/tff.py
sskk/rule/__init__.py
sskk/rule/builtin_act.py
sskk/rule/builtin_azik.py
sskk/rule/builtin_base.py
sskk/rule/builtin_normal.py