Metadata-Version: 1.0
Name: sentimental-skk
Version: 0.0.142
Summary: 三 三 ( ´_ゝ`）＜ Japanese Input Method SKK (Simple Kana to Kanji conversion) on your terminal
Home-page: https://github.com/saitoha/sentimental-skk
Author: Hayaki Saito (user@zuse.jp)
Author-email: user@zuse.jp
License: GPL v3
Keywords: skk japanese terminal
Platform: UNKNOWN
Classifier: Development Status :: 4 - Beta
Classifier: Topic :: Terminals
Classifier: Environment :: Console
Classifier: Intended Audience :: End Users/Desktop
Classifier: License :: OSI Approved :: GNU General Public License (GPL)
Classifier: Programming Language :: Python
